[
    {
        "id": "orc",
        "type": "actor",
        "name": "Orc",
        "components": {
            "characterobject": {
                "letter": "o",
                "color": "#3f7f3f"
            },
            "faction": {
                "factions": "monsters",
                "enemies": "player"
            },
            "aiMeleeChase": {},
            "fighter": {
                "hp": 10,
                "defense": 1,
                "power": 4
            }
        }
    },
    {
        "id": "troll",
        "type": "actor",
        "name": "Troll",
        "components": {
            "characterobject": {
                "letter": "T",
                "color": "#007f00"
            },
            "faction": {
                "factions": "monsters",
                "enemies": "player"
            },
            "aiMeleeChase": {},
            "fighter": {
                "hp": 16,
                "defense": 1,
                "power": 4
            }
        }
    },
    {
        "id": "ant",
        "type": "actor",
        "name": "Ant",
        "components": {
            "characterobject": {
                "letter": "a",
                "color": "#000000"
            },
            "faction": {
                "factions": "monsters",
                "enemies": "player"
            },
            "aiMeleeChase": {}
        }
    },
    {
        "id": "dragon_red",
        "type": "actor",
        "name": "Red Dragon",
        "components": {
            "characterobject": {
                "letter": "D",
                "color": "#ff0000"
            },
            "faction": {
                "factions": "monsters",
                "enemies": "player"
            },
            "aiMeleeChase": {}
        }
    },
    {
        "id": "goblin",
        "type": "actor",
        "name": "Goblin",
        "components": {
            "characterobject": {
                "letter": "g",
                "color": "#3f7f3f"
            },
            "faction": {
                "factions": "monsters",
                "enemies": "player"
            },
            "aiMeleeChase": {}
        }
    }
]